dccd/__init__.py
dccd/binance.py
dccd/bitfinex.py
dccd/dl_cc_data.py
dccd/exchange.py
dccd/gdax.py
dccd/kraken.py
dccd/poloniex.py
dccd/process_data.py
dccd/time_tools.py
dccd/continuous_dl/__init__.py
dccd/continuous_dl/bitfinex.py
dccd/continuous_dl/bitmex.py
dccd/continuous_dl/exchange.py
dccd/histo_dl/__init__.py
dccd/histo_dl/binance.py
dccd/histo_dl/exchange.py
dccd/histo_dl/gdax.py
dccd/histo_dl/kraken.py
dccd/histo_dl/poloniex.py
dccd/tests/__init__.py
dccd/tests/test_binance.py
dccd/tests/test_gdax.py
dccd/tests/test_kraken.py
dccd/tests/test_poloniex.py
dccd/tools/__init__.py
dccd/tools/date_time.py
dccd/tools/io.py
dccd/tools/websocket.py
dccd-1.1.1.dist-info/LICENSE.txt
dccd-1.1.1.dist-info/METADATA
dccd-1.1.1.dist-info/WHEEL
dccd-1.1.1.dist-info/top_level.txt
dccd-1.1.1.dist-info/RECORD
