Metadata-Version: 2.1
Name: dccd
Version: 1.1.1
Summary: Download Crypto Currenciy Data from different exchanges.
Home-page: https://github.com/ArthurBernard/Download_Crypto_Currencies_Data
Author: Arthur Bernard
Author-email: arthur.bernard.92@gmail.com
License: MIT
Platform: UNKNOWN
Classifier: Development Status :: 5 - Production/Stable
Classifier: Intended Audience :: Financial and Insurance Industry
Classifier: License :: OSI Approved :: MIT License
Classifier: Operating System :: OS Independent
Classifier: Programming Language :: Python
Classifier: Programming Language :: Python :: 3
Classifier: Programming Language :: Python :: 3.5
Classifier: Programming Language :: Python :: 3.6
Classifier: Programming Language :: Python :: 3.7
Classifier: Topic :: Database
Classifier: Topic :: Office/Business :: Financial
Requires-Dist: numpy (>=1.14.1)
Requires-Dist: pandas (>=0.22.0)
Requires-Dist: requests (>=2.18.4)
Requires-Dist: xlrd (>=1.1.0)
Requires-Dist: xlsxwriter (>=1.0.2)
Requires-Dist: websockets (>=7.0.0)
Requires-Dist: scipy (>=1.2.0)
Requires-Dist: SQLAlchemy (>=1.3.0)
